snirwhatsapp/__init__.py
snirwhatsapp/chromedriver.exe
snirwhatsapp/icon.ico
snirwhatsapp-0.0.6.dist-info/METADATA
snirwhatsapp-0.0.6.dist-info/WHEEL
snirwhatsapp-0.0.6.dist-info/top_level.txt
snirwhatsapp-0.0.6.dist-info/RECORD
