Metadata-Version: 2.1
Name: snirwhatsapp
Version: 0.0.6
Summary: automate whatsapp messages
Home-page: UNKNOWN
Author: snir dekel
Author-email: snirdekel101@gmail.com
License: MIT
Keywords: whatsapp
Platform: UNKNOWN
Classifier: Development Status :: 5 - Production/Stable
Classifier: Intended Audience :: Education
Classifier: Operating System :: Microsoft :: Windows :: Windows 10
Classifier: License :: OSI Approved :: MIT License
Classifier: Programming Language :: Python :: 3
Requires-Dist: selenium
Requires-Dist: ttkthemes
